{
  "parent": null,
  "hash": "0x92884a74858983f43096962a6c95cedd4a984aa63e6d5a7eb62ff050d57ae3dd",
  "states": {
    "0": {
      "dbContent": {
        "tablesMap": [
          [
            "elements",
            {
              "keypathList": [],
              "entriesList": [
                "{\"txStatus\":\"Transaction complete!\",\"balance\":\"2000\"}"
              ]
            }
          ]
        ]
      },
      "txErrors": [],
      "consoleErrors": [
        {
          "dappName": "AgroChain",
          "instanceId": "1",
          "errorString": "[2020-12-31T16:19:04+0800] [SEVERE] https://sentry.io/api/273496/store/?sentry_key=f59f3dd640d2429d9d0e2445a87ea8e1&sentry_version=7 - Failed to load resource: the server responded with a status of 429 (Too Many Requests)"
        },
        {
          "dappName": "AgroChain",
          "instanceId": "1",
          "errorString": "[2020-12-31T16:19:04+0800] [SEVERE] https://sentry.io/api/273496/store/?sentry_key=f59f3dd640d2429d9d0e2445a87ea8e1&sentry_version=7 - Failed to load resource: the server responded with a status of 429 (Too Many Requests)"
        },
        {
          "dappName": "AgroChain",
          "instanceId": "1",
          "errorString": "[2020-12-31T16:19:04+0800] [SEVERE] https://sentry.io/api/273496/store/?sentry_key=f59f3dd640d2429d9d0e2445a87ea8e1&sentry_version=7 - Failed to load resource: the server responded with a status of 429 (Too Many Requests)"
        }
      ],
      "contractVulReports": []
    },
    "1": {
      "dbContent": {
        "tablesMap": [
          [
            "elements",
            {
              "keypathList": [],
              "entriesList": [
                "{\"txStatus\":\"Transaction complete!\",\"balance\":\"2000\"}"
              ]
            }
          ]
        ]
      },
      "txErrors": [],
      "consoleErrors": [
        {
          "dappName": "AgroChain",
          "instanceId": "1",
          "errorString": "[2020-12-31T16:19:05+0800] [SEVERE] https://sentry.io/api/273496/store/?sentry_key=f59f3dd640d2429d9d0e2445a87ea8e1&sentry_version=7 - Failed to load resource: the server responded with a status of 429 (Too Many Requests)"
        }
      ],
      "contractVulReports": []
    },
    "2": {
      "dbContent": {
        "tablesMap": [
          [
            "elements",
            {
              "keypathList": [],
              "entriesList": [
                "{\"txStatus\":\"Transaction complete!\",\"balance\":\"2000\"}"
              ]
            }
          ]
        ]
      },
      "txErrors": [],
      "consoleErrors": [],
      "contractVulReports": []
    },
    "3": null,
    "4": {
      "dbContent": {
        "tablesMap": [
          [
            "elements",
            {
              "keypathList": [],
              "entriesList": [
                "{\"txStatus\":\"Transaction complete!\",\"balance\":\"2000\"}"
              ]
            }
          ]
        ]
      },
      "txErrors": [],
      "consoleErrors": [],
      "contractVulReports": []
    },
    "5": {
      "dbContent": {
        "tablesMap": [
          [
            "elements",
            {
              "keypathList": [],
              "entriesList": [
                "{\"txStatus\":\"Transaction complete!\",\"balance\":\"2000\"}"
              ]
            }
          ]
        ]
      },
      "txErrors": [],
      "consoleErrors": [],
      "contractVulReports": []
    },
    "6": {
      "dbContent": {
        "tablesMap": [
          [
            "elements",
            {
              "keypathList": [],
              "entriesList": [
                "{\"txStatus\":\"Transaction complete!\",\"balance\":\"2000\"}"
              ]
            }
          ]
        ]
      },
      "txErrors": [],
      "consoleErrors": [],
      "contractVulReports": []
    }
  },
  "stack": [
    "at Object.apply (chrome-extension://kdaoeelmbdcinklhldlcmmgmndjcmjpp/inpage.js:1:1247)",
    "at t.exports.sendAsync (chrome-extension://kdaoeelmbdcinklhldlcmmgmndjcmjpp/inpage.js:1:43423)",
    "at Provider.sendAsync (http://localhost:3000/app.js:42888:29)",
    "at RequestManager.sendAsync (http://localhost:3000/app.js:39258:19)",
    "at Eth.send [as sendTransaction] (http://localhost:3000/app.js:38207:42)",
    "at SolidityFunction.sendTransaction (http://localhost:3000/app.js:37274:15)",
    "at SolidityFunction.execute (http://localhost:3000/app.js:37357:37)",
    "at http://localhost:3000/app.js:43022:14",
    "at Promise._execute (http://localhost:3000/app.js:838:9)",
    "at Promise._resolveFromExecutor (http://localhost:3000/app.js:3015:18)",
    "at new Promise (http://localhost:3000/app.js:2631:14)",
    "at Contract.fundaddr (http://localhost:3000/app.js:42967:16)",
    "at set (http://localhost:3000/app.js:43859:11)",
    "at HTMLButtonElement.onclick (http://localhost:3000/:34:74)",
    "at eval (eval at executeScript (:480:16), <anonymous>:3:38)",
    "at executeScript (<anonymous>:482:30)",
    "at apply.ELEMENT (<anonymous>:487:24)",
    "at callFunction (<anonymous>:450:22)",
    "at <anonymous>:464:23",
    "at <anonymous>:465:3"
  ]
}